{
    "23": "Passive",
    "1": "Preemptive",
    "27": "On Defeat",
    "2": "1 Hit",
    "3": "2 Hits",
    "4": "3 Hits",
    "5": "Multi Hits",
    "8": "Immunity",
    "22": "Damage Reduce",
    "31": "Absorb Shield",
    "18": "Timer Reduce",
    "24": "Increase CD",
    "7": "Buff",
    "11": "Debuff",
    "12": "Card Bind",
    "19": "Skill Bind",
    "26": "Awoken Bind",
    "15": "Absorb Element",
    "20": "Absorb Combos",
    "13": "Convert Orbs",
    "34": "Special Convert Orbs",
    "29": "Convert Bombs",
    "25": "Lock Orbs",
    "32": "Lock Row",
    "33": "Lock Column",
    "14": "Gravity",
    "21": "Skyfall",
    "10": "Heal",
    "35": "Rotate Orbs",
    "36": "Unmatchable",
    "37": "RCV halved",
    "16": "Hide Orbs",
    "30": "Darkened Orbs",
    "17": "Skip turn",
    "28": "Puzzle start point fixed"
}